<?xml version='1.0' encoding='utf-8'?>
<additional><chargingStation id="cs_001" lane="5204154#6_0" startPos="31.9" endPos="36.9" power="22000" efficiency="0.95" chargeDelay="1.0" chargeInTransit="0" /><chargingStation id="cs_002" lane="-533484404#3_0" startPos="15.4" endPos="20.4" power="22000" efficiency="0.95" chargeDelay="1.0" chargeInTransit="0" /><chargingStation id="cs_003" lane="-30832143_0" startPos="1.8" endPos="6.8" power="22000" efficiency="0.95" chargeDelay="1.0" chargeInTransit="0" /><chargingStation id="cs_004" lane="-23732460_0" startPos="50.0" endPos="55.0" power="22000" efficiency="0.95" chargeDelay="1.0" chargeInTransit="0" /><chargingStation id="cs_005" lane="4602143_0" startPos="63.3" endPos="68.3" power="22000" efficiency="0.95" chargeDelay="1.0" chargeInTransit="0" /><chargingStation id="cs_006" lane="1025809837#1_0" startPos="9.5" endPos="14.5" power="22000" efficiency="0.95" chargeDelay="1.0" chargeInTransit="0" /><chargingStation id="cs_007" lane="239139835#3_0" startPos="23.1" endPos="28.1" power="22000" efficiency="0.95" chargeDelay="1.0" chargeInTransit="0" /><chargingStation id="cs_008" lane="-24324790#4_0" startPos="17.0" endPos="22.0" power="22000" efficiency="0.95" chargeDelay="1.0" chargeInTransit="0" /><chargingStation id="cs_009" lane="234349296#1_0" startPos="104.0" endPos="109.0" power="22000" efficiency="0.95" chargeDelay="1.0" chargeInTransit="0" /><chargingStation id="cs_010" lane="37933604_0" startPos="8.5" endPos="13.5" power="22000" efficiency="0.95" chargeDelay="1.0" chargeInTransit="0" /><chargingStation id="cs_011" lane="202754594#10_0" startPos="11.0" endPos="16.0" power="22000" efficiency="0.95" chargeDelay="1.0" chargeInTransit="0" /><chargingStation id="cs_012" lane="-30879353#8_0" startPos="13.3" endPos="18.3" power="22000" efficiency="0.95" chargeDelay="1.0" chargeInTransit="0" /><chargingStation id="cs_013" lane="70260063#3_0" startPos="21.9" endPos="26.9" power="22000" efficiency="0.95" chargeDelay="1.0" chargeInTransit="0" /><chargingStation id="cs_014" lane="-143625703#4_0" startPos="8.4" endPos="13.4" power="22000" efficiency="0.95" chargeDelay="1.0" chargeInTransit="0" /><chargingStation id="cs_015" lane="81634299#14_0" startPos="8.1" endPos="13.1" power="22000" efficiency="0.95" chargeDelay="1.0" chargeInTransit="0" /><chargingStation id="cs_016" lane="-55988199#8_0" startPos="11.0" endPos="16.0" power="22000" efficiency="0.95" chargeDelay="1.0" chargeInTransit="0" /><chargingStation id="cs_017" lane="754363948#3_0" startPos="18.5" endPos="23.5" power="22000" efficiency="0.95" chargeDelay="1.0" chargeInTransit="0" /><chargingStation id="cs_018" lane="4995729#3_0" startPos="42.3" endPos="47.3" power="22000" efficiency="0.95" chargeDelay="1.0" chargeInTransit="0" /><chargingStation id="cs_019" lane="-97888258#0_0" startPos="45.8" endPos="50.8" power="22000" efficiency="0.95" chargeDelay="1.0" chargeInTransit="0" /><chargingStation id="cs_020" lane="-24317001_0" startPos="24.5" endPos="29.5" power="22000" efficiency="0.95" chargeDelay="1.0" chargeInTransit="0" /><chargingStation id="cs_021" lane="82056114#11_0" startPos="24.5" endPos="29.5" power="22000" efficiency="0.95" chargeDelay="1.0" chargeInTransit="0" /><chargingStation id="cs_022" lane="23803724#1_0" startPos="4.2" endPos="9.2" power="22000" efficiency="0.95" chargeDelay="1.0" chargeInTransit="0" /><chargingStation id="cs_023" lane="-23149797#6_0" startPos="76.7" endPos="81.7" power="22000" efficiency="0.95" chargeDelay="1.0" chargeInTransit="0" /><chargingStation id="cs_024" lane="-81634298#0_0" startPos="9.5" endPos="14.5" power="22000" efficiency="0.95" chargeDelay="1.0" chargeInTransit="0" /><chargingStation id="cs_025" lane="-24316911#0_0" startPos="13.8" endPos="18.8" power="22000" efficiency="0.95" chargeDelay="1.0" chargeInTransit="0" /><chargingStation id="cs_026" lane="82021017#4_0" startPos="11.2" endPos="16.2" power="22000" efficiency="0.95" chargeDelay="1.0" chargeInTransit="0" /><chargingStation id="cs_027" lane="-28169964#0_0" startPos="47.4" endPos="52.4" power="22000" efficiency="0.95" chargeDelay="1.0" chargeInTransit="0" /><chargingStation id="cs_028" lane="7996853#2_0" startPos="2.8" endPos="7.8" power="22000" efficiency="0.95" chargeDelay="1.0" chargeInTransit="0" /><chargingStation id="cs_029" lane="70260062#7_0" startPos="0.1" endPos="5.1" power="22000" efficiency="0.95" chargeDelay="1.0" chargeInTransit="0" /><chargingStation id="cs_030" lane="-985861987#1_0" startPos="4.8" endPos="9.8" power="22000" efficiency="0.95" chargeDelay="1.0" chargeInTransit="0" /><chargingStation id="cs_031" lane="10760708#2_0" startPos="46.5" endPos="51.5" power="22000" efficiency="0.95" chargeDelay="1.0" chargeInTransit="0" /><chargingStation id="cs_032" lane="-4713086#4_0" startPos="4.5" endPos="9.5" power="22000" efficiency="0.95" chargeDelay="1.0" chargeInTransit="0" /><chargingStation id="cs_033" lane="206174219#3_0" startPos="17.7" endPos="22.7" power="22000" efficiency="0.95" chargeDelay="1.0" chargeInTransit="0" /><chargingStation id="cs_034" lane="4856806#1_0" startPos="1.5" endPos="6.5" power="22000" efficiency="0.95" chargeDelay="1.0" chargeInTransit="0" /><chargingStation id="cs_035" lane="-23275440#5_0" startPos="4.1" endPos="9.1" power="22000" efficiency="0.95" chargeDelay="1.0" chargeInTransit="0" /><chargingStation id="cs_036" lane="162481139#13_0" startPos="32.8" endPos="37.8" power="22000" efficiency="0.95" chargeDelay="1.0" chargeInTransit="0" /><chargingStation id="cs_037" lane="180596541#0_0" startPos="72.5" endPos="77.5" power="22000" efficiency="0.95" chargeDelay="1.0" chargeInTransit="0" /><chargingStation id="cs_038" lane="354340064#6_0" startPos="4.5" endPos="9.5" power="22000" efficiency="0.95" chargeDelay="1.0" chargeInTransit="0" /><chargingStation id="cs_039" lane="-504467345#0_0" startPos="9.3" endPos="14.3" power="22000" efficiency="0.95" chargeDelay="1.0" chargeInTransit="0" /><chargingStation id="cs_040" lane="30879367#0_0" startPos="26.9" endPos="31.9" power="22000" efficiency="0.95" chargeDelay="1.0" chargeInTransit="0" /><chargingStation id="cs_041" lane="202753992#1_0" startPos="88.1" endPos="93.1" power="22000" efficiency="0.95" chargeDelay="1.0" chargeInTransit="0" /><chargingStation id="cs_042" lane="-61011268_0" startPos="5.1" endPos="10.1" power="22000" efficiency="0.95" chargeDelay="1.0" chargeInTransit="0" /><chargingStation id="cs_043" lane="-1194002130#0_0" startPos="2.0" endPos="7.0" power="22000" efficiency="0.95" chargeDelay="1.0" chargeInTransit="0" /><chargingStation id="cs_044" lane="-101262451#4_0" startPos="22.7" endPos="27.7" power="22000" efficiency="0.95" chargeDelay="1.0" chargeInTransit="0" /><chargingStation id="cs_045" lane="22883542#2_0" startPos="63.9" endPos="68.9" power="22000" efficiency="0.95" chargeDelay="1.0" chargeInTransit="0" /><chargingStation id="cs_046" lane="389241496#9_0" startPos="318.2" endPos="323.2" power="22000" efficiency="0.95" chargeDelay="1.0" chargeInTransit="0" /><chargingStation id="cs_047" lane="1791_0" startPos="611.3" endPos="616.3" power="22000" efficiency="0.95" chargeDelay="1.0" chargeInTransit="0" /><chargingStation id="cs_048" lane="551670116#1_0" startPos="38.8" endPos="43.8" power="22000" efficiency="0.95" chargeDelay="1.0" chargeInTransit="0" /><chargingStation id="cs_049" lane="225018498#2_0" startPos="112.2" endPos="117.2" power="22000" efficiency="0.95" chargeDelay="1.0" chargeInTransit="0" /><chargingStation id="cs_050" lane="-26350978#2_0" startPos="26.5" endPos="31.5" power="22000" efficiency="0.95" chargeDelay="1.0" chargeInTransit="0" /><chargingStation id="cs_051" lane="47500097#2_0" startPos="61.7" endPos="66.7" power="22000" efficiency="0.95" chargeDelay="1.0" chargeInTransit="0" /><chargingStation id="cs_052" lane="-820159284_0" startPos="32.5" endPos="37.5" power="22000" efficiency="0.95" chargeDelay="1.0" chargeInTransit="0" /><chargingStation id="cs_053" lane="-41559876#0_0" startPos="6.1" endPos="11.1" power="22000" efficiency="0.95" chargeDelay="1.0" chargeInTransit="0" /><chargingStation id="cs_054" lane="4787474_0" startPos="0.2" endPos="5.2" power="22000" efficiency="0.95" chargeDelay="1.0" chargeInTransit="0" /><chargingStation id="cs_055" lane="14595332_0" startPos="51.1" endPos="56.1" power="22000" efficiency="0.95" chargeDelay="1.0" chargeInTransit="0" /><chargingStation id="cs_056" lane="204735909#9_0" startPos="19.1" endPos="24.1" power="22000" efficiency="0.95" chargeDelay="1.0" chargeInTransit="0" /><chargingStation id="cs_057" lane="80584636#4_0" startPos="21.5" endPos="26.5" power="22000" efficiency="0.95" chargeDelay="1.0" chargeInTransit="0" /><chargingStation id="cs_058" lane="1334239534#2_0" startPos="1.1" endPos="6.1" power="22000" efficiency="0.95" chargeDelay="1.0" chargeInTransit="0" /><chargingStation id="cs_059" lane="703508894#1_0" startPos="38.8" endPos="43.8" power="22000" efficiency="0.95" chargeDelay="1.0" chargeInTransit="0" /><chargingStation id="cs_060" lane="-228097381#0_0" startPos="37.5" endPos="42.5" power="22000" efficiency="0.95" chargeDelay="1.0" chargeInTransit="0" /><chargingStation id="cs_061" lane="4334681#1_0" startPos="119.4" endPos="124.4" power="22000" efficiency="0.95" chargeDelay="1.0" chargeInTransit="0" /><chargingStation id="cs_062" lane="-16199720#3_0" startPos="71.2" endPos="76.2" power="22000" efficiency="0.95" chargeDelay="1.0" chargeInTransit="0" /><chargingStation id="cs_063" lane="-22731473#4_0" startPos="3.6" endPos="8.6" power="22000" efficiency="0.95" chargeDelay="1.0" chargeInTransit="0" /><chargingStation id="cs_064" lane="402481690_0" startPos="51.9" endPos="56.9" power="22000" efficiency="0.95" chargeDelay="1.0" chargeInTransit="0" /><chargingStation id="cs_065" lane="752709968#1_0" startPos="6.0" endPos="11.0" power="22000" efficiency="0.95" chargeDelay="1.0" chargeInTransit="0" /><chargingStation id="cs_066" lane="-1199969121_0" startPos="1.7" endPos="6.7" power="22000" efficiency="0.95" chargeDelay="1.0" chargeInTransit="0" /><chargingStation id="cs_067" lane="-202753590#0_0" startPos="5.5" endPos="10.5" power="22000" efficiency="0.95" chargeDelay="1.0" chargeInTransit="0" /><chargingStation id="cs_068" lane="205819137#2_0" startPos="10.5" endPos="15.5" power="22000" efficiency="0.95" chargeDelay="1.0" chargeInTransit="0" /><chargingStation id="cs_069" lane="-61012410#7_0" startPos="38.6" endPos="43.6" power="22000" efficiency="0.95" chargeDelay="1.0" chargeInTransit="0" /><chargingStation id="cs_070" lane="-7997253#3_0" startPos="38.2" endPos="43.2" power="22000" efficiency="0.95" chargeDelay="1.0" chargeInTransit="0" /><chargingStation id="cs_071" lane="1155202863#1_0" startPos="20.3" endPos="25.3" power="22000" efficiency="0.95" chargeDelay="1.0" chargeInTransit="0" /><chargingStation id="cs_072" lane="-9048033#0_0" startPos="7.6" endPos="12.6" power="22000" efficiency="0.95" chargeDelay="1.0" chargeInTransit="0" /><chargingStation id="cs_073" lane="19784509_0" startPos="3.7" endPos="8.7" power="22000" efficiency="0.95" chargeDelay="1.0" chargeInTransit="0" /><chargingStation id="cs_074" lane="223298257#14_0" startPos="10.2" endPos="15.2" power="22000" efficiency="0.95" chargeDelay="1.0" chargeInTransit="0" /><chargingStation id="cs_075" lane="225017990#6_0" startPos="63.5" endPos="68.5" power="22000" efficiency="0.95" chargeDelay="1.0" chargeInTransit="0" /><chargingStation id="cs_076" lane="-80621115_0" startPos="4.1" endPos="9.1" power="22000" efficiency="0.95" chargeDelay="1.0" chargeInTransit="0" /><chargingStation id="cs_077" lane="-22752443#1_0" startPos="37.4" endPos="42.4" power="22000" efficiency="0.95" chargeDelay="1.0" chargeInTransit="0" /><chargingStation id="cs_078" lane="-32514987#1_0" startPos="22.9" endPos="27.9" power="22000" efficiency="0.95" chargeDelay="1.0" chargeInTransit="0" /><chargingStation id="cs_079" lane="-820159322#2_0" startPos="62.8" endPos="67.8" power="22000" efficiency="0.95" chargeDelay="1.0" chargeInTransit="0" /><chargingStation id="cs_080" lane="85363134#1_0" startPos="58.6" endPos="63.6" power="22000" efficiency="0.95" chargeDelay="1.0" chargeInTransit="0" /><chargingStation id="cs_081" lane="-760089006#5_0" startPos="30.4" endPos="35.4" power="22000" efficiency="0.95" chargeDelay="1.0" chargeInTransit="0" /><chargingStation id="cs_082" lane="1390722571#6_0" startPos="13.3" endPos="18.3" power="22000" efficiency="0.95" chargeDelay="1.0" chargeInTransit="0" /><chargingStation id="cs_083" lane="102000576#4_0" startPos="40.6" endPos="45.6" power="22000" efficiency="0.95" chargeDelay="1.0" chargeInTransit="0" /><chargingStation id="cs_084" lane="45856435#0_0" startPos="56.1" endPos="61.1" power="22000" efficiency="0.95" chargeDelay="1.0" chargeInTransit="0" /><chargingStation id="cs_085" lane="226585764#3_0" startPos="4.3" endPos="9.3" power="22000" efficiency="0.95" chargeDelay="1.0" chargeInTransit="0" /><chargingStation id="cs_086" lane="673617397#0_0" startPos="46.0" endPos="51.0" power="22000" efficiency="0.95" chargeDelay="1.0" chargeInTransit="0" /><chargingStation id="cs_087" lane="-434979140#0_0" startPos="27.4" endPos="32.4" power="22000" efficiency="0.95" chargeDelay="1.0" chargeInTransit="0" /><chargingStation id="cs_088" lane="54642157#3_0" startPos="125.5" endPos="130.5" power="22000" efficiency="0.95" chargeDelay="1.0" chargeInTransit="0" /><chargingStation id="cs_089" lane="24232511#3_0" startPos="56.3" endPos="61.3" power="22000" efficiency="0.95" chargeDelay="1.0" chargeInTransit="0" /><chargingStation id="cs_090" lane="8015456#1_0" startPos="48.5" endPos="53.5" power="22000" efficiency="0.95" chargeDelay="1.0" chargeInTransit="0" /><chargingStation id="cs_091" lane="-54643522_0" startPos="28.6" endPos="33.6" power="22000" efficiency="0.95" chargeDelay="1.0" chargeInTransit="0" /><chargingStation id="cs_092" lane="20127309#3_0" startPos="3.1" endPos="8.1" power="22000" efficiency="0.95" chargeDelay="1.0" chargeInTransit="0" /><chargingStation id="cs_093" lane="43564898#1_0" startPos="4.7" endPos="9.7" power="22000" efficiency="0.95" chargeDelay="1.0" chargeInTransit="0" /><chargingStation id="cs_094" lane="-60298325#3_0" startPos="41.7" endPos="46.7" power="22000" efficiency="0.95" chargeDelay="1.0" chargeInTransit="0" /><chargingStation id="cs_095" lane="-20903057#1_0" startPos="23.4" endPos="28.4" power="22000" efficiency="0.95" chargeDelay="1.0" chargeInTransit="0" /><chargingStation id="cs_096" lane="36142201#0_0" startPos="11.1" endPos="16.1" power="22000" efficiency="0.95" chargeDelay="1.0" chargeInTransit="0" /><chargingStation id="cs_097" lane="24299705#0_0" startPos="12.1" endPos="17.1" power="22000" efficiency="0.95" chargeDelay="1.0" chargeInTransit="0" /><chargingStation id="cs_098" lane="60674432#2_0" startPos="27.5" endPos="32.5" power="22000" efficiency="0.95" chargeDelay="1.0" chargeInTransit="0" /><chargingStation id="cs_099" lane="-82885374#4_0" startPos="38.1" endPos="43.1" power="22000" efficiency="0.95" chargeDelay="1.0" chargeInTransit="0" /><chargingStation id="cs_100" lane="-111660823#3_0" startPos="54.6" endPos="59.6" power="22000" efficiency="0.95" chargeDelay="1.0" chargeInTransit="0" /><chargingStation id="cs_101" lane="275118481#1_0" startPos="18.5" endPos="23.5" power="22000" efficiency="0.95" chargeDelay="1.0" chargeInTransit="0" /><chargingStation id="cs_102" lane="4344900#1_0" startPos="13.6" endPos="18.6" power="22000" efficiency="0.95" chargeDelay="1.0" chargeInTransit="0" /><chargingStation id="cs_103" lane="180579429#6_0" startPos="24.3" endPos="29.3" power="22000" efficiency="0.95" chargeDelay="1.0" chargeInTransit="0" /><chargingStation id="cs_104" lane="-77669321_0" startPos="53.4" endPos="58.4" power="22000" efficiency="0.95" chargeDelay="1.0" chargeInTransit="0" /><chargingStation id="cs_105" lane="25637149_0" startPos="52.5" endPos="57.5" power="22000" efficiency="0.95" chargeDelay="1.0" chargeInTransit="0" /><chargingStation id="cs_106" lane="10111720_0" startPos="1.2" endPos="6.2" power="22000" efficiency="0.95" chargeDelay="1.0" chargeInTransit="0" /><chargingStation id="cs_107" lane="249123994#2_0" startPos="41.2" endPos="46.2" power="22000" efficiency="0.95" chargeDelay="1.0" chargeInTransit="0" /><chargingStation id="cs_108" lane="-4904401#7_0" startPos="16.9" endPos="21.9" power="22000" efficiency="0.95" chargeDelay="1.0" chargeInTransit="0" /><chargingStation id="cs_109" lane="642330217#1_0" startPos="211.4" endPos="216.4" power="22000" efficiency="0.95" chargeDelay="1.0" chargeInTransit="0" /><chargingStation id="cs_110" lane="-23105062#0_0" startPos="40.8" endPos="45.8" power="22000" efficiency="0.95" chargeDelay="1.0" chargeInTransit="0" /><chargingStation id="cs_111" lane="82255114#0_0" startPos="14.3" endPos="19.3" power="22000" efficiency="0.95" chargeDelay="1.0" chargeInTransit="0" /><chargingStation id="cs_112" lane="-4856804#0_0" startPos="35.5" endPos="40.5" power="22000" efficiency="0.95" chargeDelay="1.0" chargeInTransit="0" /><chargingStation id="cs_113" lane="-27928232#1_0" startPos="14.1" endPos="19.1" power="22000" efficiency="0.95" chargeDelay="1.0" chargeInTransit="0" /><chargingStation id="cs_114" lane="-625312656#2_0" startPos="3.8" endPos="8.8" power="22000" efficiency="0.95" chargeDelay="1.0" chargeInTransit="0" /><chargingStation id="cs_115" lane="-24317470#1_0" startPos="2.3" endPos="7.3" power="22000" efficiency="0.95" chargeDelay="1.0" chargeInTransit="0" /><chargingStation id="cs_116" lane="-374975169#1_0" startPos="9.0" endPos="14.0" power="22000" efficiency="0.95" chargeDelay="1.0" chargeInTransit="0" /><chargingStation id="cs_117" lane="-6448489_0" startPos="12.6" endPos="17.6" power="22000" efficiency="0.95" chargeDelay="1.0" chargeInTransit="0" /><chargingStation id="cs_118" lane="-31092177#11_0" startPos="13.4" endPos="18.4" power="22000" efficiency="0.95" chargeDelay="1.0" chargeInTransit="0" /><chargingStation id="cs_119" lane="60066261#0_0" startPos="61.5" endPos="66.5" power="22000" efficiency="0.95" chargeDelay="1.0" chargeInTransit="0" /><chargingStation id="cs_120" lane="-355341269#7_0" startPos="34.7" endPos="39.7" power="22000" efficiency="0.95" chargeDelay="1.0" chargeInTransit="0" /><chargingStation id="cs_121" lane="-7277290#2_0" startPos="16.4" endPos="21.4" power="22000" efficiency="0.95" chargeDelay="1.0" chargeInTransit="0" /><chargingStation id="cs_122" lane="-29425419#1_0" startPos="4.2" endPos="9.2" power="22000" efficiency="0.95" chargeDelay="1.0" chargeInTransit="0" /><chargingStation id="cs_123" lane="-26235657#1_0" startPos="20.2" endPos="25.2" power="22000" efficiency="0.95" chargeDelay="1.0" chargeInTransit="0" /><chargingStation id="cs_124" lane="28261827#0_0" startPos="26.9" endPos="31.9" power="22000" efficiency="0.95" chargeDelay="1.0" chargeInTransit="0" /><chargingStation id="cs_125" lane="-22587676#1_0" startPos="41.8" endPos="46.8" power="22000" efficiency="0.95" chargeDelay="1.0" chargeInTransit="0" /><chargingStation id="cs_126" lane="164087238#3_0" startPos="4.9" endPos="9.9" power="22000" efficiency="0.95" chargeDelay="1.0" chargeInTransit="0" /><chargingStation id="cs_127" lane="-151100320#3_0" startPos="8.0" endPos="13.0" power="22000" efficiency="0.95" chargeDelay="1.0" chargeInTransit="0" /><chargingStation id="cs_128" lane="-91894962_0" startPos="104.4" endPos="109.4" power="22000" efficiency="0.95" chargeDelay="1.0" chargeInTransit="0" /><chargingStation id="cs_129" lane="595322007#6_0" startPos="4.7" endPos="9.7" power="22000" efficiency="0.95" chargeDelay="1.0" chargeInTransit="0" /><chargingStation id="cs_130" lane="20902015#3_0" startPos="7.1" endPos="12.1" power="22000" efficiency="0.95" chargeDelay="1.0" chargeInTransit="0" /><chargingStation id="cs_131" lane="-56743564#6_0" startPos="48.5" endPos="53.5" power="22000" efficiency="0.95" chargeDelay="1.0" chargeInTransit="0" /><chargingStation id="cs_132" lane="-250479796#9_0" startPos="43.5" endPos="48.5" power="22000" efficiency="0.95" chargeDelay="1.0" chargeInTransit="0" /><chargingStation id="cs_133" lane="23732264#0_0" startPos="10.3" endPos="15.3" power="22000" efficiency="0.95" chargeDelay="1.0" chargeInTransit="0" /><chargingStation id="cs_134" lane="30879129#2_0" startPos="3.8" endPos="8.8" power="22000" efficiency="0.95" chargeDelay="1.0" chargeInTransit="0" /><chargingStation id="cs_135" lane="24246237#1_0" startPos="0.9" endPos="5.9" power="22000" efficiency="0.95" chargeDelay="1.0" chargeInTransit="0" /><chargingStation id="cs_136" lane="-5218780#2_0" startPos="7.7" endPos="12.7" power="22000" efficiency="0.95" chargeDelay="1.0" chargeInTransit="0" /><chargingStation id="cs_137" lane="132006281#5_0" startPos="5.3" endPos="10.3" power="22000" efficiency="0.95" chargeDelay="1.0" chargeInTransit="0" /><chargingStation id="cs_138" lane="-951982740_0" startPos="0.6" endPos="5.6" power="22000" efficiency="0.95" chargeDelay="1.0" chargeInTransit="0" /><chargingStation id="cs_139" lane="-23471558#3_0" startPos="44.0" endPos="49.0" power="22000" efficiency="0.95" chargeDelay="1.0" chargeInTransit="0" /><chargingStation id="cs_140" lane="23314822#4_0" startPos="22.5" endPos="27.5" power="22000" efficiency="0.95" chargeDelay="1.0" chargeInTransit="0" /><chargingStation id="cs_141" lane="-34307607#1_0" startPos="198.3" endPos="203.3" power="22000" efficiency="0.95" chargeDelay="1.0" chargeInTransit="0" /><chargingStation id="cs_142" lane="-731208273#0_0" startPos="41.6" endPos="46.6" power="22000" efficiency="0.95" chargeDelay="1.0" chargeInTransit="0" /><chargingStation id="cs_143" lane="-39609754#4_0" startPos="5.5" endPos="10.5" power="22000" efficiency="0.95" chargeDelay="1.0" chargeInTransit="0" /><chargingStation id="cs_144" lane="-61430474#0_0" startPos="9.8" endPos="14.8" power="22000" efficiency="0.95" chargeDelay="1.0" chargeInTransit="0" /><chargingStation id="cs_145" lane="-82389343#1_0" startPos="11.6" endPos="16.6" power="22000" efficiency="0.95" chargeDelay="1.0" chargeInTransit="0" /><chargingStation id="cs_146" lane="4515791#6_0" startPos="20.7" endPos="25.7" power="22000" efficiency="0.95" chargeDelay="1.0" chargeInTransit="0" /><chargingStation id="cs_147" lane="80343139#0_0" startPos="45.6" endPos="50.6" power="22000" efficiency="0.95" chargeDelay="1.0" chargeInTransit="0" /><chargingStation id="cs_148" lane="30879246#1_0" startPos="27.3" endPos="32.3" power="22000" efficiency="0.95" chargeDelay="1.0" chargeInTransit="0" /><chargingStation id="cs_149" lane="154494735#8_0" startPos="55.6" endPos="60.6" power="22000" efficiency="0.95" chargeDelay="1.0" chargeInTransit="0" /><chargingStation id="cs_150" lane="8515615#3_0" startPos="72.9" endPos="77.9" power="22000" efficiency="0.95" chargeDelay="1.0" chargeInTransit="0" /><chargingStation id="cs_151" lane="-24232690#0_0" startPos="32.5" endPos="37.5" power="22000" efficiency="0.95" chargeDelay="1.0" chargeInTransit="0" /><chargingStation id="cs_152" lane="417625399#0_0" startPos="16.3" endPos="21.3" power="22000" efficiency="0.95" chargeDelay="1.0" chargeInTransit="0" /><chargingStation id="cs_153" lane="31092317#2_0" startPos="16.3" endPos="21.3" power="22000" efficiency="0.95" chargeDelay="1.0" chargeInTransit="0" /><chargingStation id="cs_154" lane="-4252150#4_0" startPos="4.0" endPos="9.0" power="22000" efficiency="0.95" chargeDelay="1.0" chargeInTransit="0" /><chargingStation id="cs_155" lane="1317111186_0" startPos="21.5" endPos="26.5" power="22000" efficiency="0.95" chargeDelay="1.0" chargeInTransit="0" /><chargingStation id="cs_156" lane="-203516660#2_0" startPos="4.2" endPos="9.2" power="22000" efficiency="0.95" chargeDelay="1.0" chargeInTransit="0" /><chargingStation id="cs_157" lane="-60235366_0" startPos="6.0" endPos="11.0" power="22000" efficiency="0.95" chargeDelay="1.0" chargeInTransit="0" /><chargingStation id="cs_158" lane="49049425#0_0" startPos="35.5" endPos="40.5" power="22000" efficiency="0.95" chargeDelay="1.0" chargeInTransit="0" /><chargingStation id="cs_159" lane="8751311_0" startPos="0.4" endPos="5.4" power="22000" efficiency="0.95" chargeDelay="1.0" chargeInTransit="0" /><chargingStation id="cs_160" lane="-82494355_0" startPos="49.7" endPos="54.7" power="22000" efficiency="0.95" chargeDelay="1.0" chargeInTransit="0" /><chargingStation id="cs_161" lane="23105653_0" startPos="19.5" endPos="24.5" power="22000" efficiency="0.95" chargeDelay="1.0" chargeInTransit="0" /><chargingStation id="cs_162" lane="23732043#7_0" startPos="57.5" endPos="62.5" power="22000" efficiency="0.95" chargeDelay="1.0" chargeInTransit="0" /><chargingStation id="cs_163" lane="198964340#5_0" startPos="70.5" endPos="75.5" power="22000" efficiency="0.95" chargeDelay="1.0" chargeInTransit="0" /><chargingStation id="cs_164" lane="183451043#0_0" startPos="2.6" endPos="7.6" power="22000" efficiency="0.95" chargeDelay="1.0" chargeInTransit="0" /><chargingStation id="cs_165" lane="-82209852#8_0" startPos="27.9" endPos="32.9" power="22000" efficiency="0.95" chargeDelay="1.0" chargeInTransit="0" /><chargingStation id="cs_166" lane="-82724603#4_0" startPos="4.8" endPos="9.8" power="22000" efficiency="0.95" chargeDelay="1.0" chargeInTransit="0" /><chargingStation id="cs_167" lane="23844147#0_0" startPos="28.4" endPos="33.4" power="22000" efficiency="0.95" chargeDelay="1.0" chargeInTransit="0" /><chargingStation id="cs_168" lane="-31091985#4_0" startPos="34.6" endPos="39.6" power="22000" efficiency="0.95" chargeDelay="1.0" chargeInTransit="0" /><chargingStation id="cs_169" lane="8015461#1_0" startPos="23.2" endPos="28.2" power="22000" efficiency="0.95" chargeDelay="1.0" chargeInTransit="0" /><chargingStation id="cs_170" lane="28169963_0" startPos="27.7" endPos="32.7" power="22000" efficiency="0.95" chargeDelay="1.0" chargeInTransit="0" /><chargingStation id="cs_171" lane="530761062_0" startPos="11.0" endPos="16.0" power="22000" efficiency="0.95" chargeDelay="1.0" chargeInTransit="0" /><chargingStation id="cs_172" lane="23732274_0" startPos="22.4" endPos="27.4" power="22000" efficiency="0.95" chargeDelay="1.0" chargeInTransit="0" /><chargingStation id="cs_173" lane="-45773042#0_0" startPos="1.2" endPos="6.2" power="22000" efficiency="0.95" chargeDelay="1.0" chargeInTransit="0" /><chargingStation id="cs_174" lane="-642722362#1_0" startPos="30.1" endPos="35.1" power="22000" efficiency="0.95" chargeDelay="1.0" chargeInTransit="0" /><chargingStation id="cs_175" lane="-31000816#0_0" startPos="109.8" endPos="114.8" power="22000" efficiency="0.95" chargeDelay="1.0" chargeInTransit="0" /><chargingStation id="cs_176" lane="-30880849#0_0" startPos="17.4" endPos="22.4" power="22000" efficiency="0.95" chargeDelay="1.0" chargeInTransit="0" /><chargingStation id="cs_177" lane="45483384#2_0" startPos="40.9" endPos="45.9" power="22000" efficiency="0.95" chargeDelay="1.0" chargeInTransit="0" /><chargingStation id="cs_178" lane="-82739291_0" startPos="15.4" endPos="20.4" power="22000" efficiency="0.95" chargeDelay="1.0" chargeInTransit="0" /><chargingStation id="cs_179" lane="28672938#3_0" startPos="21.3" endPos="26.3" power="22000" efficiency="0.95" chargeDelay="1.0" chargeInTransit="0" /><chargingStation id="cs_180" lane="-80621219#0_0" startPos="11.7" endPos="16.7" power="22000" efficiency="0.95" chargeDelay="1.0" chargeInTransit="0" /><chargingStation id="cs_181" lane="-24730984#10_0" startPos="28.0" endPos="33.0" power="22000" efficiency="0.95" chargeDelay="1.0" chargeInTransit="0" /><chargingStation id="cs_182" lane="-24300124#0_0" startPos="24.7" endPos="29.7" power="22000" efficiency="0.95" chargeDelay="1.0" chargeInTransit="0" /><chargingStation id="cs_183" lane="4569987#9_0" startPos="5.7" endPos="10.7" power="22000" efficiency="0.95" chargeDelay="1.0" chargeInTransit="0" /><chargingStation id="cs_184" lane="198962610#1_0" startPos="10.7" endPos="15.7" power="22000" efficiency="0.95" chargeDelay="1.0" chargeInTransit="0" /><chargingStation id="cs_185" lane="62150195#0_0" startPos="60.8" endPos="65.8" power="22000" efficiency="0.95" chargeDelay="1.0" chargeInTransit="0" /><chargingStation id="cs_186" lane="26478788_0" startPos="41.3" endPos="46.3" power="22000" efficiency="0.95" chargeDelay="1.0" chargeInTransit="0" /><chargingStation id="cs_187" lane="255331058#5_0" startPos="22.7" endPos="27.7" power="22000" efficiency="0.95" chargeDelay="1.0" chargeInTransit="0" /><chargingStation id="cs_188" lane="9503861#0_0" startPos="22.1" endPos="27.1" power="22000" efficiency="0.95" chargeDelay="1.0" chargeInTransit="0" /><chargingStation id="cs_189" lane="24730984#4_0" startPos="8.0" endPos="13.0" power="22000" efficiency="0.95" chargeDelay="1.0" chargeInTransit="0" /><chargingStation id="cs_190" lane="-23948640#1_0" startPos="32.7" endPos="37.7" power="22000" efficiency="0.95" chargeDelay="1.0" chargeInTransit="0" /><chargingStation id="cs_191" lane="60931360_0" startPos="84.4" endPos="89.4" power="22000" efficiency="0.95" chargeDelay="1.0" chargeInTransit="0" /><chargingStation id="cs_192" lane="-24317765#0_0" startPos="0.4" endPos="5.4" power="22000" efficiency="0.95" chargeDelay="1.0" chargeInTransit="0" /><chargingStation id="cs_193" lane="24317517#4_0" startPos="15.7" endPos="20.7" power="22000" efficiency="0.95" chargeDelay="1.0" chargeInTransit="0" /><chargingStation id="cs_194" lane="23392887#3_0" startPos="38.3" endPos="43.3" power="22000" efficiency="0.95" chargeDelay="1.0" chargeInTransit="0" /><chargingStation id="cs_195" lane="-61229200_0" startPos="10.7" endPos="15.7" power="22000" efficiency="0.95" chargeDelay="1.0" chargeInTransit="0" /><chargingStation id="cs_196" lane="-55685637#3_0" startPos="0.6" endPos="5.6" power="22000" efficiency="0.95" chargeDelay="1.0" chargeInTransit="0" /><chargingStation id="cs_197" lane="-80584699#1_0" startPos="28.4" endPos="33.4" power="22000" efficiency="0.95" chargeDelay="1.0" chargeInTransit="0" /><chargingStation id="cs_198" lane="4856731#5_0" startPos="5.6" endPos="10.6" power="22000" efficiency="0.95" chargeDelay="1.0" chargeInTransit="0" /><chargingStation id="cs_199" lane="-940159537#0_0" startPos="11.8" endPos="16.8" power="22000" efficiency="0.95" chargeDelay="1.0" chargeInTransit="0" /><chargingStation id="cs_200" lane="-28380024_0" startPos="2.7" endPos="7.7" power="22000" efficiency="0.95" chargeDelay="1.0" chargeInTransit="0" /><chargingStation id="cs_201" lane="26706061#0_0" startPos="3.3" endPos="8.3" power="22000" efficiency="0.95" chargeDelay="1.0" chargeInTransit="0" /><chargingStation id="cs_202" lane="-642714753_0" startPos="70.3" endPos="75.3" power="22000" efficiency="0.95" chargeDelay="1.0" chargeInTransit="0" /><chargingStation id="cs_203" lane="-1367201936#2_0" startPos="9.4" endPos="14.4" power="22000" efficiency="0.95" chargeDelay="1.0" chargeInTransit="0" /><chargingStation id="cs_204" lane="24299944#2_0" startPos="7.2" endPos="12.2" power="22000" efficiency="0.95" chargeDelay="1.0" chargeInTransit="0" /><chargingStation id="cs_205" lane="732972958#1_0" startPos="4.8" endPos="9.8" power="22000" efficiency="0.95" chargeDelay="1.0" chargeInTransit="0" /><chargingStation id="cs_206" lane="-8080070#0_0" startPos="8.1" endPos="13.1" power="22000" efficiency="0.95" chargeDelay="1.0" chargeInTransit="0" /><chargingStation id="cs_207" lane="172384775#1_0" startPos="19.1" endPos="24.1" power="22000" efficiency="0.95" chargeDelay="1.0" chargeInTransit="0" /><chargingStation id="cs_208" lane="242773833#7_0" startPos="26.6" endPos="31.6" power="22000" efficiency="0.95" chargeDelay="1.0" chargeInTransit="0" /><chargingStation id="cs_209" lane="38788472#2_0" startPos="37.1" endPos="42.1" power="22000" efficiency="0.95" chargeDelay="1.0" chargeInTransit="0" /><chargingStation id="cs_210" lane="80584513_0" startPos="3.8" endPos="8.8" power="22000" efficiency="0.95" chargeDelay="1.0" chargeInTransit="0" /><chargingStation id="cs_211" lane="-10750732#4_0" startPos="32.8" endPos="37.8" power="22000" efficiency="0.95" chargeDelay="1.0" chargeInTransit="0" /><chargingStation id="cs_212" lane="-223996498#15_0" startPos="30.2" endPos="35.2" power="22000" efficiency="0.95" chargeDelay="1.0" chargeInTransit="0" /><chargingStation id="cs_213" lane="62310522#2_0" startPos="8.1" endPos="13.1" power="22000" efficiency="0.95" chargeDelay="1.0" chargeInTransit="0" /><chargingStation id="cs_214" lane="578672579#0_0" startPos="31.6" endPos="36.6" power="22000" efficiency="0.95" chargeDelay="1.0" chargeInTransit="0" /><chargingStation id="cs_215" lane="-38325916_0" startPos="2.1" endPos="7.1" power="22000" efficiency="0.95" chargeDelay="1.0" chargeInTransit="0" /></additional>